piscola/__init__.py
piscola/_version.py
piscola/extinction_correction.py
piscola/filters_class.py
piscola/gaussian_process.py
piscola/lightcurves_class.py
piscola/sn_class.py
piscola/utils.py
piscola/__pycache__/__init__.cpython-313.pyc
piscola/__pycache__/_version.cpython-313.pyc
piscola/__pycache__/extinction_correction.cpython-313.pyc
piscola/__pycache__/filters_class.cpython-313.pyc
piscola/__pycache__/gaussian_process.cpython-313.pyc
piscola/__pycache__/lightcurves_class.cpython-313.pyc
piscola/__pycache__/sn_class.cpython-313.pyc
piscola/__pycache__/utils.cpython-313.pyc
piscola/filters/README.txt
piscola/filters/2MASS/2MASS_H.dat
piscola/filters/2MASS/2MASS_J.dat
piscola/filters/2MASS/2MASS_Ks.dat
piscola/filters/2MASS/README.txt
piscola/filters/4Shooter2/4Shooter2_B.dat
piscola/filters/4Shooter2/4Shooter2_I.dat
piscola/filters/4Shooter2/4Shooter2_R.dat
piscola/filters/4Shooter2/4Shooter2_U.dat
piscola/filters/4Shooter2/4Shooter2_V.dat
piscola/filters/4Shooter2/README.txt
piscola/filters/4Shooter2/response_type.txt
piscola/filters/ATLAS/ATLAS_c.dat
piscola/filters/ATLAS/ATLAS_o.dat
piscola/filters/ATLAS/README.txt
piscola/filters/Bessell/Bessell_B.dat
piscola/filters/Bessell/Bessell_I.dat
piscola/filters/Bessell/Bessell_R.dat
piscola/filters/Bessell/Bessell_U.dat
piscola/filters/Bessell/Bessell_V.dat
piscola/filters/Bessell/README.txt
piscola/filters/CFA4/README.txt
piscola/filters/CFA4/p1_B.dat
piscola/filters/CFA4/p1_U.dat
piscola/filters/CFA4/p1_V.dat
piscola/filters/CFA4/p1_i.dat
piscola/filters/CFA4/p1_r.dat
piscola/filters/CFA4/p2_B.dat
piscola/filters/CFA4/p2_U.dat
piscola/filters/CFA4/p2_V.dat
piscola/filters/CFA4/p2_i.dat
piscola/filters/CFA4/p2_r.dat
piscola/filters/CSP/README.txt
piscola/filters/CSP/V_LC3009_texas_WLcorr_atm.txt~
piscola/filters/CSP/V_LC3014_texas_WLcorr_atm.txt~
piscola/filters/CSP/V_LC9844_texas_WLcorr_atm.txt~
piscola/filters/CSP/V_LC9844_texax_WLcorr_atm.txt~
piscola/filters/CSP/csp_B.dat
piscola/filters/CSP/csp_V.dat
piscola-3.0.0.dist-info/LICENSE
piscola-3.0.0.dist-info/METADATA
piscola-3.0.0.dist-info/WHEEL
piscola-3.0.0.dist-info/top_level.txt
piscola-3.0.0.dist-info/RECORD
