Metadata-Version: 2.1
Name: piscola
Version: 3.0.0
Summary: Type Ia Supernova Light-curve fitting code
Home-page: https://github.com/temuller/piscola
Author: Tomás Enrique Müller Bravo
Author-email: t.e.muller-bravo@soton.ac.uk
License: MIT
Classifier: Programming Language :: Python :: 3
Classifier: License :: OSI Approved :: MIT License
Classifier: Operating System :: OS Independent
Requires-Python: >=3.9
License-File: LICENSE
Requires-Dist: numpy>=2.0.0
Requires-Dist: pandas
Requires-Dist: matplotlib
Requires-Dist: peakutils
Requires-Dist: requests
Requires-Dist: sfdmap2
Requires-Dist: extinction>=0.4.7
Requires-Dist: astropy
Requires-Dist: scipy
Requires-Dist: jax; "linux" in sys_platform or "win" in sys_platform
Requires-Dist: jaxopt
Requires-Dist: tinygp
